sliding_puzzles/__init__.py
sliding_puzzles/env.py
sliding_puzzles/wrappers.py
sliding_puzzles-0.9.2.dist-info/LICENSE
sliding_puzzles-0.9.2.dist-info/METADATA
sliding_puzzles-0.9.2.dist-info/WHEEL
sliding_puzzles-0.9.2.dist-info/entry_points.txt
sliding_puzzles-0.9.2.dist-info/top_level.txt
sliding_puzzles-0.9.2.dist-info/RECORD
