Metadata-Version: 2.2
Name: sliding-puzzles
Version: 0.9.2
Summary: A richer sliding blocks puzzle RL environment.
Home-page: https://github.com/bryanoliveira/sliding-puzzles-gym
Author: Bryan L M Oliveira
Author-email: bryanlmoliveira@gmail.com
Project-URL: Bug Tracker, https://github.com/bryanoliveira/sliding-puzzles-gym/issues
Classifier: Development Status :: 4 - Beta
Classifier: Programming Language :: Python :: 3
Classifier: License :: OSI Approved :: MIT License
Classifier: Operating System :: POSIX :: Linux
Classifier: Operating System :: Microsoft :: Windows
Classifier: Operating System :: MacOS
Classifier: Topic :: Games/Entertainment :: Simulation
Classifier: Topic :: Scientific/Engineering :: Artificial Intelligence
Requires-Python: >=3.7
License-File: LICENSE
Requires-Dist: gymnasium
Requires-Dist: matplotlib
Requires-Dist: numpy
Requires-Dist: Pillow
Requires-Dist: click
Requires-Dist: requests
